{
  "name": "Railway MCP Monday.com Integration",
  "nodes": [
    {
      "parameters": {
        "httpMethod": "POST",
        "path": "monday-email-update",
        "responseMode": "responseNode"
      },
      "id": "webhook-trigger",
      "name": "Webhook Trigger",
      "type": "n8n-nodes-base.webhook",
      "typeVersion": 1,
      "position": [240, 300]
    },
    {
      "parameters": {
        "url": "https://mcp-server-for-mondaycom-dify-automation-production.up.railway.app/api/monday/update-email",
        "sendHeaders": true,
        "headerParameters": {
          "parameters": [
            {
              "name": "Content-Type",
              "value": "application/json"
            }
          ]
        },
        "sendBody": true,
        "bodyParameters": {
          "parameters": [
            {
              "name": "itemName",
              "value": "={{ $json.itemName || 'Task' }}"
            },
            {
              "name": "email",
              "value": "={{ $json.email || 'william@gmail.com' }}"
            }
          ]
        },
        "options": {}
      },
      "id": "railway-mcp-api",
      "name": "Railway MCP API",
      "type": "n8n-nodes-base.httpRequest",
      "typeVersion": 4.1,
      "position": [460, 300]
    },
    {
      "parameters": {
        "respondWith": "json",
        "responseBody": "={{ { success: true, message: 'Email updated via Railway MCP server', data: $json, source: 'Railway MCP Server' } }}"
      },
      "id": "response",
      "name": "Response",
      "type": "n8n-nodes-base.respondToWebhook",
      "typeVersion": 1,
      "position": [680, 300]
    }
  ],
  "connections": {
    "Webhook Trigger": {
      "main": [
        [
          {
            "node": "Railway MCP API",
            "type": "main",
            "index": 0
          }
        ]
      ]
    },
    "Railway MCP API": {
      "main": [
        [
          {
            "node": "Response",
            "type": "main",
            "index": 0
          }
        ]
      ]
    }
  },
  "settings": {
    "executionOrder": "v1"
  }
} 